nexus/__init__.py
nexus/cache.py
nexus/client.py
nexus/exceptions.py
nexus/requests.py
nexus/websockets.py
nexus/api_types/__init__.py
nexus/api_types/v1.py
nexus/models/__init__.py
nexus/models/account.py
nexus/models/sessions.py
tycho_nexus-0.0.11.dist-info/licenses/LICENSE
tycho_nexus-0.0.11.dist-info/METADATA
tycho_nexus-0.0.11.dist-info/WHEEL
tycho_nexus-0.0.11.dist-info/top_level.txt
tycho_nexus-0.0.11.dist-info/RECORD
