Metadata-Version: 2.4
Name: tycho.nexus
Version: 0.0.11
Summary: The official Python API wrapper for Nexus, by Tycho
Home-page: https://github.com/TychoTeam/nexus-py
Author: Tycho
Author-email: mail@tycho.team
License: MIT
Keywords: nexus,tycho
Classifier: Framework :: AsyncIO
Requires-Python: >=3.8
License-File: LICENSE
Requires-Dist: httpx
Requires-Dist: asyncio
Requires-Dist: websockets
Dynamic: author
Dynamic: author-email
Dynamic: classifier
Dynamic: description
Dynamic: description-content-type
Dynamic: home-page
Dynamic: keywords
Dynamic: license
Dynamic: license-file
Dynamic: requires-dist
Dynamic: requires-python
Dynamic: summary
